Workbook

Sheet Dashboard
A1: TurboPitch Financial Dashboard
A2: Investor-ready projection summary with model-linked KPIs and readiness flags.
A4: Key Metric | B4: Year 1 | C4: Year 2 | D4: Year 3 | F4: Investor Snapshot | G4: Assessment | H4: Status | I4: Notes | J4: Metric | K4: Year 1 | L4: Year 2 | M4: Year 3
A5: Revenue | B5: ='Financial Model'!B8 | C5: ='Financial Model'!C8 | D5: ='Financial Model'!D8 | F5: Industry | G5: Vertical SaaS / AI Software | H5: Green | I5: Category detected from the founder input. | J5: Revenue | K5: ='Financial Model'!B8 | L5: ='Financial Model'!C8 | M5: ='Financial Model'!D8
A6: Gross Profit | B6: ='Financial Model'!B14 | C6: ='Financial Model'!C14 | D6: ='Financial Model'!D14 | F6: Customer Segment | G6: B2B / SMB Operators | H6: Green | I6: Customer segment inferred from the startup description. | J6: Net Income | K6: ='Financial Model'!B27 | L6: ='Financial Model'!C27 | M6: ='Financial Model'!D27
A7: Gross Margin % | B7: ='Financial Model'!B15 | C7: ='Financial Model'!C15 | D7: ='Financial Model'!D15 | F7: Overall Readiness | G7: Needs Work | H7: Yellow | I7: Reality Engine sees some real-world issues that may weaken investor credibility. | J7: Ending Cash | K7: ='Financial Model'!B29 | L7: ='Financial Model'!C29 | M7: ='Financial Model'!D29
A8: Operating Income | B8: ='Financial Model'!B22 | C8: ='Financial Model'!C22 | D8: ='Financial Model'!D22 | F8: Pricing Realism | G8: Needs Support | H8: Yellow | I8: Price of $5.00 may be too low for a B2B operator software concept and could understate value. | J8: Investor Haircut Revenue | K8: ='Financial Model'!B35 | L8: ='Financial Model'!C35 | M8: ='Financial Model'!D35
A9: Net Income | B9: ='Financial Model'!B27 | C9: ='Financial Model'!C27 | D9: ='Financial Model'!D27 | F9: Sales Volume | G9: Unrealistic | H9: Red | I9: Year 1 unit target of 80,000 is aggressive for a B2B software rollout and needs support from pipeline, conversion rate, paid-location count, retention, and rollout capacity.
A10: Ending Cash | B10: ='Financial Model'!B29 | C10: ='Financial Model'!C29 | D10: ='Financial Model'!D29 | F10: Growth Assumptions | G10: Plausible | H10: Green | I10: Growth path is within the selected operating-model benchmark ranges.
F11: Margin Quality | G11: Healthy | H11: Green | I11: Gross Margin is within the typical Vertical SaaS / AI Software benchmark range.
F12: Cash Viability | G12: Needs Runway Support | H12: Yellow | I12: Ending cash remains positive, but Year 1 losses require clear runway and milestone support.
A15: P&L Summary
A16: Line Item | B16: Year 1 | C16: Year 2 | D16: Year 3
A17: Units | B17: ='Financial Model'!B6 | C17: ='Financial Model'!C6 | D17: ='Financial Model'!D6
A18: Revenue | B18: ='Financial Model'!B8 | C18: ='Financial Model'!C8 | D18: ='Financial Model'!D8
A19: COGS | B19: ='Financial Model'!B13 | C19: ='Financial Model'!C13 | D19: ='Financial Model'!D13
A20: Gross Profit | B20: ='Financial Model'!B14 | C20: ='Financial Model'!C14 | D20: ='Financial Model'!D14
A21: Gross Margin % | B21: ='Financial Model'!B15 | C21: ='Financial Model'!C15 | D21: ='Financial Model'!D15
A22: Operating Expenses | B22: ='Financial Model'!B20 | C22: ='Financial Model'!C20 | D22: ='Financial Model'!D20
A23: Operating Income | B23: ='Financial Model'!B22 | C23: ='Financial Model'!C22 | D23: ='Financial Model'!D22
A24: Taxes | B24: ='Financial Model'!B26 | C24: ='Financial Model'!C26 | D24: ='Financial Model'!D26
A25: Net Income | B25: ='Financial Model'!B27 | C25: ='Financial Model'!C27 | D25: ='Financial Model'!D27
A26: Ending Cash | B26: ='Financial Model'!B29 | C26: ='Financial Model'!C29 | D26: ='Financial Model'!D29

Sheet Assumptions
A1: TurboPitch Financial Model - Assumptions
A2: Blue font = hardcoded user input. Yellow fill = key input / investor-sensitive assumption.
A4: Input | B4: Value | C4: Units | D4: Source / Logic | E4: Notes
A5: Startup Idea | B5: Create a pitch deck and financial model for AutoFlow AI, an AI-powered software platform for independent car washes that predicts demand, optimizes staffing, tracks chemical and water usage, and automatically recommends pricing or promotions based on weather, traffic, and local events. | C5: Text | D5: Founder input | E5: Keep concise for investor export.
A6: Industry | B6: Vertical SaaS / AI Software | C6: Category | D6: Founder / TurboPitch detection
A7: Customer Segment | B7: B2B / SMB Operators | C7: Category | D7: TurboPitch detection
A8: Assumption Mode | B8: Manual | C8: Scenario | D8: User selected | E8: Can be expanded to Base / Conservative / Investor haircut.
A9: Price per Unit | B9: 5 | C9: $ / unit | D9: Founder input | E9: Define unit clearly: customer, order, seat, transaction.
A10: Year 1 Units Sold | B10: 80000 | C10: units | D10: Founder input | E10: Primary investor challenge based on benchmark review.
A11: Year 2 Growth Rate | B11: 0.6 | C11: % | D11: Founder input
A12: Year 3 Growth Rate | B12: 0.4 | C12: % | D12: Founder input
A13: Cost per Unit | B13: 1.2 | C13: $ / unit | D13: Founder input | E13: Likely understated if hosting, support, delivery ops, and payment fees are missing.
A14: Operating Expense % | B14: 0.25 | C14: % of revenue | D14: Founder input | E14: May be low for go-to-market-heavy startup.
A15: Fixed Annual Overhead | B15: 300000 | C15: $ / year | D15: Founder input
A16: Starting Cash | B16: 600000 | C16: $ | D16: Founder input
A17: Tax Rate | B17: 0.21 | C17: % | D17: Default model assumption | E17: Placeholder. Replace with actual tax treatment.
A18: Investor Pushback % | B18: 0.25 | C18: % haircut | D18: Investor feedback | E18: Used for conservative pressure-test case.
A19: Investor Feedback | B19: Investor says revenue assumptions are too aggressive and early customer acquisition may be unrealistic. | C19: Text | D19: User input | E19: Used to guide review flags.

Sheet Financial Model
A1: Three-Year Projection Model
A2: Formula-driven model. Black font = formulas. Blue font = hardcoded assumptions on Assumptions tab.
A4: Revenue Build
A5: Line Item | B5: Year 1 | C5: Year 2 | D5: Year 3 | E5: Formula / Notes
A6: Units | B6: ='Assumptions'!B10 | C6: =B6*(1+'Assumptions'!B11) | D6: =C6*(1+'Assumptions'!B12) | E6: Y1 hardcoded from Assumptions; Y2/Y3 apply growth assumptions.
A7: Average Selling Price | B7: ='Assumptions'!B9 | C7: ='Assumptions'!B9 | D7: ='Assumptions'!B9 | E7: Price per unit held constant.
A8: Revenue | B8: =B6*B7 | C8: =C6*C7 | D8: =D6*D7 | E8: Units x Average Selling Price.
A9: Revenue Growth | B9: =0 | C9: =IFERROR(C8/B8-1,0) | D9: =IFERROR(D8/C8-1,0) | E9: YoY growth.
A11: Cost of Sales
A12: Cost per Unit | B12: ='Assumptions'!B13 | C12: ='Assumptions'!B13 | D12: ='Assumptions'!B13 | E12: COGS per unit held constant.
A13: COGS | B13: =B6*B12 | C13: =C6*C12 | D13: =D6*D12 | E13: Units x Cost per Unit.
A14: Gross Profit | B14: =B8-B13 | C14: =C8-C13 | D14: =D8-D13 | E14: Revenue - COGS.
A15: Gross Margin % | B15: =IFERROR(B14/B8,0) | C15: =IFERROR(C14/C8,0) | D15: =IFERROR(D14/D8,0) | E15: Gross Profit / Revenue.
A17: Operating Expenses
A18: Variable OpEx | B18: =B8*'Assumptions'!B14 | C18: =C8*'Assumptions'!B14 | D18: =D8*'Assumptions'!B14 | E18: Revenue x Operating Expense %.
A19: Fixed Annual Overhead | B19: ='Assumptions'!B15 | C19: ='Assumptions'!B15 | D19: ='Assumptions'!B15 | E19: Fixed overhead from Assumptions.
A20: Total Operating Expenses | B20: =B18+B19 | C20: =C18+C19 | D20: =D18+D19 | E20: Variable OpEx + Fixed Overhead.
A21: OpEx % of Revenue | B21: =IFERROR(B20/B8,0) | C21: =IFERROR(C20/C8,0) | D21: =IFERROR(D20/D8,0) | E21: Total OpEx / Revenue.
A22: Operating Income | B22: =B14-B20 | C22: =C14-C20 | D22: =D14-D20 | E22: Gross Profit - Total Operating Expenses.
A24: Cash Flow / Profitability
A25: Beginning Cash | B25: ='Assumptions'!B16 | C25: =B29 | D25: =C29 | E25: Y1 starts with cash input; future years roll forward.
A26: Taxes | B26: =MAX(0,B22*'Assumptions'!B17) | C26: =MAX(0,C22*'Assumptions'!B17) | D26: =MAX(0,D22*'Assumptions'!B17) | E26: MAX(0, Operating Income x Tax Rate).
A27: Net Income | B27: =B22-B26 | C27: =C22-C26 | D27: =D22-D26 | E27: Operating Income - Taxes.
A28: Net Margin % | B28: =IFERROR(B27/B8,0) | C28: =IFERROR(C27/C8,0) | D28: =IFERROR(D27/D8,0) | E28: Net Income / Revenue.
A29: Ending Cash | B29: =B25+B27 | C29: =C25+C27 | D29: =D25+D27 | E29: Beginning Cash + Net Income.
A33: Investor Haircut Case
A34: Line Item | B34: Year 1 | C34: Year 2 | D34: Year 3 | E34: Formula / Notes
A35: Revenue @ Investor Haircut | B35: =B8*(1-'Assumptions'!B18) | C35: =C8*(1-'Assumptions'!B18) | D35: =D8*(1-'Assumptions'!B18) | E35: Revenue reduced by Investor Pushback %.
A36: Net Income @ Investor Haircut | B36: =B35-(B13*(1-'Assumptions'!B18))-(B18*(1-'Assumptions'!B18))-B19-MAX(0,(B35-(B13*(1-'Assumptions'!B18))-(B18*(1-'Assumptions'!B18))-B19)*'Assumptions'!B17) | C36: =C35-(C13*(1-'Assumptions'!B18))-(C18*(1-'Assumptions'!B18))-C19-MAX(0,(C35-(C13*(1-'Assumptions'!B18))-(C18*(1-'Assumptions'!B18))-C19)*'Assumptions'!B17) | D36: =D35-(D13*(1-'Assumptions'!B18))-(D18*(1-'Assumptions'!B18))-D19-MAX(0,(D35-(D13*(1-'Assumptions'!B18))-(D18*(1-'Assumptions'!B18))-D19)*'Assumptions'!B17) | E36: Simple pressure-test: revenue haircut with variable COGS/OpEx partially flexed.
A37: Ending Cash @ Investor Haircut | B37: ='Assumptions'!B16+B36 | C37: =B37+C36 | D37: =C37+D36 | E37: Starting cash + cumulative haircut case income.

Sheet Investor Review
A1: Investor Review & Pressure-Test Notes
A2: This tab translates the model into likely investor questions and cleanup actions.
A4: Readiness Flags
A5: Category | B5: Metric | C5: Current Value | D5: Investor Read | E5: Recommended Fix
A6: Traction | B6: Year 1 Units | C6: ='Financial Model'!B6 | D6: Red | E6: Define whether units are paid locations, subscriptions, active accounts, or transactions, then support the target with pipeline and conversion math.
A7: Unit Economics | B7: Gross Margin % | C7: ='Financial Model'!B15 | D7: Green | E7: Validate hosting, data, onboarding, customer support, payment processing, and implementation costs.
A8: Growth | B8: Year 2 Growth | C8: ='Assumptions'!B11 | D8: Green | E8: Tie growth to paid customer acquisition, retention, expansion revenue, and sales capacity.
A9: Growth | B9: Year 3 Growth | C9: ='Assumptions'!B12 | D9: Green | E9: Tie growth to paid customer acquisition, retention, expansion revenue, and sales capacity.
A10: Operating Model | B10: Total OpEx % of Revenue | C10: ='Financial Model'!B21 | D10: Orange | E10: Break out Sales & Marketing, Product/R&D, G&A, implementation, and customer success.
A11: Liquidity | B11: Ending Cash | C11: ='Financial Model'!B29 | D11: Green | E11: Connect the cash plan to burn, runway, milestone timing, and any required funding round.
A14: Investor Questions to Prepare
A15: Question | B15: Why It Matters | C15: Founder Prep
A16: What exactly is one unit? | B16: Unit definition determines whether 80,000 units is realistic. | C16: Clarify whether units are paid locations, subscriptions, active accounts, monthly transactions, or monitored sites.
A17: What costs are included in COGS? | B17: Gross margin depends on what is included below the line. | C17: Add hosting, data, implementation, onboarding, customer support, payment fees, and AI infrastructure costs.
A18: How will you acquire 80,000 units in Year 1? | B18: Customer acquisition is the biggest model risk. | C18: Show funnel math: target accounts, outreach volume, pilot conversion, paid conversion, churn, and expansion.
A19: Why is OpEx only 25% of revenue before fixed overhead? | B19: Growth-stage software companies usually need meaningful S&M, product, and support investment. | C19: Break out Sales & Marketing, Product/R&D, G&A, implementation, and customer success costs.

Sheet Benchmark Feedback
A1: Benchmark Feedback
A2: Internal benchmark heuristics used to flag assumptions that investors may challenge.
A4: Benchmark Findings
A5: Category | B5: Status | C5: Feedback | D5: Benchmark Basis
A6: Gross Margin | B6: Green | C6: Gross Margin is within the typical Vertical SaaS / AI Software benchmark range. | D6: Internal range: 50%–85%
A7: Year 2 Growth | B7: Green | C7: Year 2 Growth is within the typical Vertical SaaS / AI Software benchmark range. | D7: Internal range: 50%–150%
A8: Year 3 Growth | B8: Green | C8: Year 3 Growth is within the typical Vertical SaaS / AI Software benchmark range. | D8: Internal range: 30%–100%
A9: Total OpEx Ratio | B9: Orange | C9: Total OpEx Ratio of 100% is above the typical benchmark range and needs stronger support. | D9: Internal range: 40%–75%
A10: Year 1 Volume | B10: Red | C10: Year 1 volume is above the typical benchmark range and needs stronger demand evidence. | D10: Internal range: 1,000–75,000
A11: Suggested Adjustment | B11: Action | C11: Clarify the unit definition, reduce or support Year 1 volume with bottom-up pipeline math, and validate gross margin with hosting, support, onboarding, and AI infrastructure costs. | D11: Investor readiness adjustment

Sheet Reality Engine
A1: Reality Engine Review
A2: Real-world credibility checks for assumptions before sending to investors.
A4: Reality Checks
A5: Check | B5: Assessment | C5: Status | D5: Finance Comment
A6: Customer Segment Detection | B6: Detected customer segment: B2B / SMB Operators | C6: Green | D6: B2B economics need buyer, sales cycle, and ACV definition.
A7: Pricing Market Fit | B7: Price of $5.00 may be too low for a B2B operator software concept and could understate value. | C7: Yellow | D7: Clarify whether $5 is monthly, per order, per route, per location, or per transaction.
A8: Adoption Realism | B8: Year 1 unit target of 80,000 is aggressive for a B2B software rollout and needs support from pipeline, conversion rate, paid-location count, retention, and rollout capacity. | C8: Red | D8: Replace top-down unit volume with bottom-up funnel logic.
A9: Growth Realism | B9: Growth path is within the selected operating-model benchmark ranges. | C9: Green | D9: Tie growth to GTM capacity and customer retention assumptions.
A10: Operating Model Reality | B10: Total OpEx is 100% of Year 1 revenue (including $300,000 fixed overhead), above the Vertical SaaS / AI Software benchmark range. | C10: Orange | D10: Add department-level OpEx build.
A11: Financial Assumption Reality | B11: Gross margin is 76.0% and ending cash does not show an obvious funding gap. | C11: Green | D11: Add direct support, infrastructure, and delivery-related costs.
A12: Overall | B12: Reality Engine sees some real-world issues that may weaken investor credibility. | C12: Yellow | D12: Investors will focus on unit definition, margin quality, and demand proof.

Sheet Methodology
A1: Methodology & Finance Model Conventions
A2: Explains the structure, color logic, and limitations of this projection model.
A4: Model Architecture
A5: Section | B5: Purpose | C5: Finance Standard Applied | D5: Notes
A6: Assumptions | B6: Centralizes all editable inputs. | C6: Hardcoded inputs in blue; key drivers highlighted yellow. | D6: Avoids burying assumptions in formulas.
A7: Financial Model | B7: Calculates revenue, margins, OpEx, profit, and cash. | C7: Formula-driven calculations in black. | D7: Built as a clean 3-year projection.
A8: Dashboard | B8: Summarizes KPIs and investor readiness. | C8: Linked outputs in green. | D8: Designed for founder/investor review.
A9: Investor Review | B9: Translates numbers into likely investor concerns. | C9: Pressure-test framing. | D9: Focuses on supportability, not just math.
A10: Benchmark Feedback | B10: Compares assumptions to internal benchmark ranges. | C10: Status flags and model-risk explanation. | D10: Should be updated with real market evidence.
A11: Reality Engine | B11: Checks whether assumptions are believable operationally. | C11: Qualitative validation layer. | D11: Not a substitute for primary research.
A14: Color Legend
A15: Color | B15: Meaning | C15: Example | D15: Why It Matters
A16: Blue font | B16: Hardcoded input | C16: Price per Unit | D16: Signals user-editable assumptions.
A17: Black font | B17: Formula / calculation | C17: Revenue = Units x Price | D17: Keeps calculations auditable.
A18: Green font | B18: Link to another worksheet | C18: Dashboard KPI links | D18: Shows cross-sheet pull-through.
A19: Yellow fill | B19: Key assumption / needs attention | C19: Year 1 Units Sold | D19: Highlights investor-sensitive drivers.
A20: Red / Green / Yellow status | B20: Risk flag | C20: Readiness status | D20: Quick visual read for investors/founders.
